Metadata-Version: 2.1
Name: odoo14-addon-fiscal-epos-print
Version: 14.0.1.0.1
Summary: ePOS-Print XML Fiscal Printer Driver - Stampanti Epson compatibili: FP81II, FP90III
Home-page: https://github.com/OCA/l10n-italy
Author: Odoo Community Association (OCA), Agile Business Group, Leonardo Donelli, TAKOBI, Level Prime Srl
Author-email: support@odoo-community.org
License: AGPL-3
Platform: UNKNOWN
Classifier: Programming Language :: Python
Classifier: Framework :: Odoo
Classifier: Framework :: Odoo :: 14.0
Classifier: License :: OSI Approved :: GNU Affero General Public License v3
Requires-Python: >=3.6
Requires-Dist: odoo (<14.1dev,>=14.0a)
